neuralprophet/__init__.py
neuralprophet/__main__.py
neuralprophet/_version.py
neuralprophet/components/README.md
neuralprophet/components/__init__.py
neuralprophet/components/base.py
neuralprophet/components/future_regressors/__init__.py
neuralprophet/components/future_regressors/base.py
neuralprophet/components/future_regressors/linear.py
neuralprophet/components/future_regressors/neural_nets.py
neuralprophet/components/future_regressors/shared_neural_nets.py
neuralprophet/components/future_regressors/shared_neural_nets_coef.py
neuralprophet/components/router.py
neuralprophet/components/seasonality/__init__.py
neuralprophet/components/seasonality/base.py
neuralprophet/components/seasonality/fourier.py
neuralprophet/components/trend/__init__.py
neuralprophet/components/trend/base.py
neuralprophet/components/trend/linear.py
neuralprophet/components/trend/piecewise_linear.py
neuralprophet/components/trend/static.py
neuralprophet/configure.py
neuralprophet/custom_loss_metrics.py
neuralprophet/data/process.py
neuralprophet/data/split.py
neuralprophet/data/transform.py
neuralprophet/df_utils.py
neuralprophet/forecaster.py
neuralprophet/hdays_utils.py
neuralprophet/logger.py
neuralprophet/np_types.py
neuralprophet/plot_forecast_matplotlib.py
neuralprophet/plot_forecast_plotly.py
neuralprophet/plot_model_parameters_matplotlib.py
neuralprophet/plot_model_parameters_plotly.py
neuralprophet/plot_utils.py
neuralprophet/time_dataset.py
neuralprophet/time_net.py
neuralprophet/torch_prophet.py
neuralprophet/uncertainty.py
neuralprophet/utils.py
neuralprophet/utils_metrics.py
neuralprophet/utils_torch.py
neuralprophet-0.8.0.dist-info/LICENSE
neuralprophet-0.8.0.dist-info/METADATA
neuralprophet-0.8.0.dist-info/WHEEL
neuralprophet-0.8.0.dist-info/RECORD
