Metadata-Version: 2.1
Name: neuralprophet
Version: 0.8.0
Summary: NeuralProphet is an easy to learn framework for interpretable time series forecasting.
License: MIT
Author: Oskar Triebe
Author-email: triebe@stanford.edu
Requires-Python: >=3.9,<4.0
Classifier: Development Status :: 4 - Beta
Classifier: License :: OSI Approved :: MIT License
Classifier: Natural Language :: English
Classifier: Operating System :: OS Independent
Classifier: Operating System :: POSIX :: Linux
Classifier: Programming Language :: Python :: 3
Classifier: Programming Language :: Python :: 3.9
Classifier: Programming Language :: Python :: 3.10
Classifier: Programming Language :: Python :: 3.11
Provides-Extra: live
Provides-Extra: plotly-resampler
Requires-Dist: captum (>=0.6.0)
Requires-Dist: holidays (>=0.41)
Requires-Dist: livelossplot (>=0.5.5) ; extra == "live"
Requires-Dist: matplotlib (>=3.5.3,<4.0.0)
Requires-Dist: nbformat (>=5.8.0,<6.0.0)
Requires-Dist: numpy (>=1.25.0,<2.0.0)
Requires-Dist: pandas (>=2.0.0,<3.0.0)
Requires-Dist: plotly (>=5.13.1,<6.0.0)
Requires-Dist: plotly-resampler (>=0.9.2,<0.10.0) ; (python_version < "3.12") and (extra == "plotly-resampler")
Requires-Dist: pytorch-lightning (>=1.9.4,<2.0.0)
Requires-Dist: tensorboard (>=2.11.2,<3.0.0)
Requires-Dist: torch (>=2.0.0,<3.0.0)
Requires-Dist: torchmetrics (>=1.0.0,<2.0.0)
Requires-Dist: typing-extensions (>=4.5.0,<5.0.0)
Project-URL: Homepage, https://github.com/ourownstory/neural_prophet
